dsps/__init__.py
dsps/attenuation_kernels.py
dsps/diffstar_ew_kernels.py
dsps/diffstar_photometry.py
dsps/diffstar_photometry_kernels.py
dsps/equivalent_width.py
dsps/flat_wcdm.py
dsps/load_diffstar_data.py
dsps/load_fsps_data.py
dsps/mzr.py
dsps/photometry.py
dsps/photometry_kernels.py
dsps/remnant_mass.py
dsps/sfh_model.py
dsps/stellar_ages.py
dsps/surviving_mstar.py
dsps/utils.py
dsps/weighted_ssps.py
dsps/weighted_table_interpolation.py
dsps/zh_model.py
dsps/data/fsps_lsst_mags_zobs.npy
dsps/data/fsps_lsst_mags_zobs_imet_20_iage_5.npy
dsps/data/fsps_lsst_mags_zobs_imet_2_iage_90.npy
dsps/data/fsps_ssp_imet_20_iage_5.npy
dsps/data/fsps_ssp_imet_2_iage_90.npy
dsps/data/log_age.npy
dsps/data/lsst_g_transmission.npy
dsps/data/lsst_i_transmission.npy
dsps/data/lsst_r_transmission.npy
dsps/data/lsst_u_transmission.npy
dsps/data/lsst_y_transmission.npy
dsps/data/lsst_z_transmission.npy
dsps/data/zlegend.npy
dsps/tests/__init__.py
dsps/tests/retrieve_fake_fsps_data.py
dsps/tests/test_attenuation.py
dsps/tests/test_diffstar_ew_kernels.py
dsps/tests/test_diffstar_photometry.py
dsps/tests/test_diffstar_photometry_kernels.py
dsps/tests/test_equivalent_width.py
dsps/tests/test_flat_wcdm.py
dsps/tests/test_mzr.py
dsps/tests/test_photometry.py
dsps/tests/test_photometry_kernels.py
dsps/tests/test_remnant_mass.py
dsps/tests/test_retrieve_fake_fsps_data.py
dsps/tests/test_sfh_model.py
dsps/tests/test_stellar_ages.py
dsps/tests/test_surviving_mstar.py
dsps/tests/test_utils.py
dsps/tests/test_weighted_ssps.py
dsps/tests/test_zh_model.py
dsps/tests/testing_data/calzetti_2000_attenuation.txt
dsps/tests/testing_data/calzetti_2000_k_lambda.txt
dsps/tests/testing_data/calzetti_2000_wavelength_microns.txt
dsps/tests/testing_data/chabrier_mstar_surviving.txt
dsps/tests/testing_data/chabrier_mstar_surviving_norem.txt
dsps/tests/testing_data/galazzi_etal05_mzr.dat
dsps/tests/testing_data/kirby_etal13_mzr.dat
dsps/tests/testing_data/kroupa_mstar_surviving.txt
dsps-0.1.0.dist-info/LICENSE
dsps-0.1.0.dist-info/METADATA
dsps-0.1.0.dist-info/WHEEL
dsps-0.1.0.dist-info/top_level.txt
dsps-0.1.0.dist-info/RECORD
